.pre-commit-hooks.yaml
hooks/__init__.py
hooks/_lib/__init__.py
hooks/_lib/git.py
hooks/_lib/gitlab.py
hooks/commit_msg/__init__.py
hooks/commit_msg/commit_msg_tk.py
hooks/pre_commit/__init__.py
hooks/pre_commit/pre_commit_tk.py
hooks/prepare_commit_msg/__init__.py
hooks/prepare_commit_msg/prepare_commit_msg_tk.py
pre_commit_sdlcgov_hooks-1.1.0.dist-info/METADATA
pre_commit_sdlcgov_hooks-1.1.0.dist-info/WHEEL
pre_commit_sdlcgov_hooks-1.1.0.dist-info/entry_points.txt
pre_commit_sdlcgov_hooks-1.1.0.dist-info/licenses/LICENSE
pre_commit_sdlcgov_hooks-1.1.0.dist-info/RECORD
