Metadata-Version: 2.4
Name: pre-commit-sdlcgov-hooks
Version: 1.1.0
Project-URL: Homepage, https://gitlab.com/Kencho1/pre-commit-sdlcgov-hooks
Project-URL: Repository, https://gitlab.com/Kencho1/pre-commit-sdlcgov-hooks
Author: Jesús Alonso Abad
License-Expression: MIT
License-File: LICENSE
Classifier: Development Status :: 5 - Production/Stable
Classifier: License :: OSI Approved :: MIT License
Classifier: Natural Language :: English
Classifier: Operating System :: OS Independent
Classifier: Programming Language :: Python :: 3
Classifier: Programming Language :: Python :: 3 :: Only
Classifier: Topic :: Software Development
Classifier: Topic :: Software Development :: Quality Assurance
Classifier: Topic :: Software Development :: Version Control
Classifier: Topic :: Software Development :: Version Control :: Git
Classifier: Typing :: Typed
Requires-Python: >=3.9
Requires-Dist: gitpython~=3.1
